{"client":"Thunder Client","collectionName":"Postgres_Gorm","dateExported":"2022-11-27T14:41:36.212Z","version":"1.1","folders":[],"requests":[{"_id":"d7e33e06-9900-4165-a8e9-fc7f46068687","colId":"a7ea725a-d416-43c0-9392-812ae6590e5b","containerId":"","name":"createBook","url":"http://localhost:3000/api/create_books","method":"POST","sortNum":10000,"created":"2022-11-27T14:14:39.031Z","modified":"2022-11-27T14:17:18.363Z","headers":[],"params":[],"body":{"type":"json","raw":"{\n  \"author\": \"Tanmay Vaish\",\n  \"title\": \"Develop Her\",\n  \"publisher\": \"Some Random Shit\"\n}","form":[]},"tests":[]},{"_id":"791554bb-0c35-4b08-8a5f-29b780f2c934","colId":"a7ea725a-d416-43c0-9392-812ae6590e5b","containerId":"","name":"getBooks","url":"http://localhost:3000/api/get_books","method":"GET","sortNum":30000,"created":"2022-11-27T14:19:04.512Z","modified":"2022-11-27T14:19:13.187Z","headers":[],"params":[],"tests":[]},{"_id":"6b1950e2-67c1-4c0b-b6ce-af921f8bdb78","colId":"a7ea725a-d416-43c0-9392-812ae6590e5b","containerId":"","name":"getBookByID","url":"http://localhost:3000/api/get_book/1","method":"GET","sortNum":40000,"created":"2022-11-27T14:19:45.343Z","modified":"2022-11-27T14:20:48.682Z","headers":[],"params":[],"tests":[]},{"_id":"aaa70e36-ce77-4a6c-8160-0459557e5271","colId":"a7ea725a-d416-43c0-9392-812ae6590e5b","containerId":"","name":"deleteBooks","url":"http://localhost:3000/api/delete_books/1","method":"DELETE","sortNum":50000,"created":"2022-11-27T14:21:10.917Z","modified":"2022-11-27T14:22:15.313Z","headers":[],"params":[],"tests":[]}]}
